mycroft_ptt_client/__init__.py
mycroft_ptt_client/__main__.py
mycroft_ptt_client-0.0.1a0.dist-info/LICENSE
mycroft_ptt_client-0.0.1a0.dist-info/METADATA
mycroft_ptt_client-0.0.1a0.dist-info/WHEEL
mycroft_ptt_client-0.0.1a0.dist-info/entry_points.txt
mycroft_ptt_client-0.0.1a0.dist-info/top_level.txt
mycroft_ptt_client-0.0.1a0.dist-info/RECORD
