Metadata-Version: 2.1
Name: mycroft-ptt-client
Version: 0.0.1a0
Summary: Mycroft Push-To-Talk Client
Home-page: https://github.com/AIIX/mycroft_ptt_client
Author: Aditya Mehra
Author-email: aix.m@outlook.com
License: Apache
Keywords: mycroft ptt daemon client
Platform: UNKNOWN
License-File: LICENSE
Requires-Dist: python-libinput
Requires-Dist: mycroft-messagebus-client
